pysmartwater/__init__.py
pysmartwater/api_async.py
pysmartwater/api_sync.py
pysmartwater/const.py
pysmartwater/data.py
pysmartwater/tasks.py
pysmartwater-1.0.0.dist-info/licenses/LICENSE
pysmartwater-1.0.0.dist-info/METADATA
pysmartwater-1.0.0.dist-info/WHEEL
pysmartwater-1.0.0.dist-info/top_level.txt
pysmartwater-1.0.0.dist-info/RECORD
