Metadata-Version: 2.4
Name: pysmartwater
Version: 1.0.0
Summary: Python library to communicate with Smart Water servers
Author-email: Anko Hanse <anko_hanse@hotmail.com>
Project-URL: Homepage, https://github.com/ankohanse/pysmartwater
Project-URL: Issues, https://github.com/ankohanse/pysmartwater/issues
Classifier: Programming Language :: Python :: 3
Classifier: License :: OSI Approved :: GNU General Public License v3 or later (GPLv3+)
Classifier: Operating System :: OS Independent
Requires-Python: >=3.8
License-File: LICENSE
Requires-Dist: PyJWT
Requires-Dist: google-cloud-firestore~=2.20
Provides-Extra: tests
Requires-Dist: pytest; extra == "tests"
Requires-Dist: pytest-asyncio; extra == "tests"
Dynamic: license-file
